TronDecode.py
trondecode-1.1.dist-info/LICENSE
trondecode-1.1.dist-info/METADATA
trondecode-1.1.dist-info/WHEEL
trondecode-1.1.dist-info/RECORD
